[
  {
    "id": "dangerous-rumors",
    "titulo": "Dangerous Rumors",
    "descripcion": "Investiga los rumores sobre monstruos extraños que han aparecido en las afueras de Prontera. Esta misión te llevará a descubrir una amenaza creciente que podría afectar a todo el reino.",
    "dificultad": 1,
    "nivel": "20-30",
    "fecha": "2025-03-10",
    "imagen": "assets/images/ro/romisiones/dangerous_rumors.jpg",
    "url": "pages/ro/romisiones/dangerousrumors.html",
    "recompensas": {
      "exp": 10000,
      "items": ["Poción x10"],
      "zeny": 5000,
      "skills": []
    },
    "tags": ["principiante", "exp", "item"]
  },
  {
    "id": "cursed-spirit",
    "titulo": "Cursed Spirit",
    "descripcion": "Un espíritu maldito ha sido avistado en el Castillo de Geffen. Los aventureros valientes que se atrevan a investigar descubrirán una historia trágica y tendrán la oportunidad de liberar al espíritu de su sufrimiento.",
    "dificultad": 2,
    "nivel": "40-50",
    "fecha": "2025-03-15",
    "imagen": "assets/images/ro/romisiones/cursed_spirit.jpg",
    "url": "pages/ro/romisiones/cursedspirit.html",
    "recompensas": {
      "exp": 30000,
      "items": ["Ghost Armor"],
      "zeny": 15000,
      "skills": []
    },
    "tags": ["intermedio", "exp", "item"]
  },
  {
    "id": "friendship-test",
    "titulo": "Friendship Test",
    "descripcion": "Ayuda a un grupo de amigos a resolver sus diferencias mediante una serie de pruebas que demostrarán el verdadero valor de la amistad. Una misión perfecta para nuevos jugadores.",
    "dificultad": 1,
    "nivel": "10-20",
    "fecha": "2025-03-12",
    "imagen": "assets/images/ro/romisiones/friendship_test.jpg",
    "url": "pages/ro/romisiones/friendship.html",
    "recompensas": {
      "exp": 5000,
      "items": [],
      "zeny": 2000,
      "skills": []
    },
    "tags": ["principiante", "exp"]
  },
  {
    "id": "ancient-artifact",
    "titulo": "Ancient Artifact",
    "descripcion": "Embárcate en la búsqueda de un artefacto antiguo con poderes extraordinarios. Esta peligrosa misión te llevará a través de múltiples mazmorras y te enfrentará a enemigos formidables.",
    "dificultad": 3,
    "nivel": "70+",
    "fecha": "2025-04-02",
    "imagen": "assets/images/ro/romisiones/ancient_artifact.jpg",
    "url": "pages/ro/romisiones/ancient-artifact.html",
    "recompensas": {
      "exp": 80000,
      "items": ["Ancient Relic"],
      "zeny": 50000,
      "skills": ["Skill Especial"]
    },
    "tags": ["avanzado", "exp", "item", "skill"]
  },
  {
    "id": "city-in-peril",
    "titulo": "City in Peril",
    "descripcion": "La ciudad de Alberta está siendo atacada por piratas. Únete a la defensa de la ciudad y protege a sus habitantes antes de que sea demasiado tarde.",
    "dificultad": 2,
    "nivel": "35-45",
    "fecha": "2025-03-25",
    "imagen": "assets/images/ro/romisiones/city_in_peril.jpg",
    "url": "pages/ro/romisiones/city-in-peril.html",
    "recompensas": {
      "exp": 25000,
      "items": [],
      "zeny": 30000,
      "skills": []
    },
    "tags": ["intermedio", "exp", "zeny"]
  },
  {
    "id": "training-novice",
    "titulo": "Training the Novice",
    "descripcion": "Ayuda a entrenar a un grupo de novatos en las artes del combate. Esta misión es perfecta para jugadores nuevos que quieren aprender los fundamentos del juego.",
    "dificultad": 1,
    "nivel": "1-10",
    "fecha": "2025-03-05",
    "imagen": "assets/images/ro/romisiones/training_novice.jpg",
    "url": "pages/ro/romisiones/training-novice.html",
    "recompensas": {
      "exp": 3000,
      "items": [],
      "zeny": 1000,
      "skills": ["Habilidad Básica"]
    },
    "tags": ["principiante", "exp", "skill"]
  },
  {
    "id": "mvp-challenge",
    "titulo": "MVP Challenge",
    "descripcion": "Un torneo especial ha sido organizado para los aventureros más valientes. Enfrenta a los MVPs más poderosos y gana recompensas únicas.",
    "dificultad": 3,
    "nivel": "90+",
    "fecha": "2025-04-15",
    "imagen": "assets/images/ro/romisiones/mvp_challenge.jpg",
    "url": "pages/ro/romisiones/mvp-challenge.html",
    "recompensas": {
      "exp": 100000,
      "items": ["MVP Card Box"],
      "zeny": 75000,
      "skills": []
    },
    "tags": ["avanzado", "exp", "item", "evento"]
  },
  {
    "id": "annual-festival",
    "titulo": "Annual Festival",
    "descripcion": "Participa en el festival anual de Prontera y disfruta de actividades especiales y misiones únicas disponibles sólo durante esta temporada.",
    "dificultad": 1,
    "nivel": "Todos los niveles",
    "fecha": "2025-04-01",
    "imagen": "assets/images/ro/romisiones/annual_festival.jpg",
    "url": "pages/ro/romisiones/annual-festival.html",
    "recompensas": {
      "exp": 15000,
      "items": ["Festival Hat"],
      "zeny": 10000,
      "skills": []
    },
    "tags": ["principiante", "intermedio", "avanzado", "exp", "item", "evento"]
  }
]
